odoo/addons/stock_available_exclude_location/README.rst
odoo/addons/stock_available_exclude_location/__init__.py
odoo/addons/stock_available_exclude_location/__manifest__.py
odoo/addons/stock_available_exclude_location/i18n/it.po
odoo/addons/stock_available_exclude_location/i18n/stock_available_exclude_location.pot
odoo/addons/stock_available_exclude_location/models/__init__.py
odoo/addons/stock_available_exclude_location/models/product_product.py
odoo/addons/stock_available_exclude_location/models/res_company.py
odoo/addons/stock_available_exclude_location/models/res_config_settings.py
odoo/addons/stock_available_exclude_location/readme/CONFIGURE.rst
odoo/addons/stock_available_exclude_location/readme/CONTRIBUTORS.rst
odoo/addons/stock_available_exclude_location/readme/DESCRIPTION.rst
odoo/addons/stock_available_exclude_location/static/description/icon.png
odoo/addons/stock_available_exclude_location/static/description/index.html
odoo/addons/stock_available_exclude_location/tests/__init__.py
odoo/addons/stock_available_exclude_location/tests/test_exclude_location.py
odoo/addons/stock_available_exclude_location/views/res_config_settings.xml
odoo_addon_stock_available_exclude_location-16.0.1.0.0.4.dist-info/METADATA
odoo_addon_stock_available_exclude_location-16.0.1.0.0.4.dist-info/WHEEL
odoo_addon_stock_available_exclude_location-16.0.1.0.0.4.dist-info/top_level.txt
odoo_addon_stock_available_exclude_location-16.0.1.0.0.4.dist-info/RECORD
