Metadata-Version: 2.1
Name: odoo-addon-stock_available_exclude_location
Version: 16.0.1.0.0.4
Summary: Exclude locations for product available quantities
Home-page: https://github.com/OCA/stock-logistics-availability
Author: Escodoo,Odoo Community Association (OCA)
Author-email: support@odoo-community.org
License: AGPL-3
Classifier: Programming Language :: Python
Classifier: Framework :: Odoo
Classifier: Framework :: Odoo :: 16.0
Classifier: License :: OSI Approved :: GNU Affero General Public License v3
Classifier: Development Status :: 3 - Alpha
Requires-Python: >=3.10
Requires-Dist: odoo-addon-stock-available-base-exclude-location<16.1dev,>=16.0dev
Requires-Dist: odoo-addon-stock-location-children<16.1dev,>=16.0dev
Requires-Dist: odoo<16.1dev,>=16.0a
